camml/__init__.py
camml/clustering.py
camml/coral.py
camml/cv2dnn.py
camml/draw.py
camml-0.0.4.dist-info/DESCRIPTION.rst
camml-0.0.4.dist-info/METADATA
camml-0.0.4.dist-info/RECORD
camml-0.0.4.dist-info/WHEEL
camml-0.0.4.dist-info/metadata.json
camml-0.0.4.dist-info/top_level.txt
