Metadata-Version: 2.0
Name: camml
Version: 0.0.4
Summary: A package of ML components for CTL field camera systems. 
Home-page: UNKNOWN
Author: Conservation Technology Lab at the San Diego Zoo Wildlife Alliance
License: MIT
Platform: UNKNOWN
Classifier: Programming Language :: Python :: 3
Classifier: License :: OSI Approved :: MIT License
Classifier: Development Status :: 2 - Pre-Alpha
Classifier: Intended Audience :: Science/Research
Classifier: Operating System :: POSIX :: Linux
Classifier: Topic :: Scientific/Engineering
Requires-Dist: opencv-python
Requires-Dist: pillow
